nuxeo/__init__.py
nuxeo/client.py
nuxeo/comments.py
nuxeo/constants.py
nuxeo/directories.py
nuxeo/documents.py
nuxeo/endpoint.py
nuxeo/exceptions.py
nuxeo/groups.py
nuxeo/models.py
nuxeo/operations.py
nuxeo/tasks.py
nuxeo/uploads.py
nuxeo/users.py
nuxeo/utils.py
nuxeo/workflows.py
nuxeo/auth/__init__.py
nuxeo/auth/base.py
nuxeo/auth/basic.py
nuxeo/auth/jwt.py
nuxeo/auth/oauth2.py
nuxeo/auth/portal_sso.py
nuxeo/auth/token.py
nuxeo/auth/utils.py
nuxeo/handlers/__init__.py
nuxeo/handlers/default.py
nuxeo/handlers/s3.py
nuxeo/tcp/__init__.py
nuxeo/tcp/tcp_keep_alive_probes.py
nuxeo-6.1.2.dist-info/LICENSE.txt
nuxeo-6.1.2.dist-info/METADATA
nuxeo-6.1.2.dist-info/WHEEL
nuxeo-6.1.2.dist-info/top_level.txt
nuxeo-6.1.2.dist-info/RECORD
