Metadata-Version: 2.1
Name: nuxeo
Version: 6.1.2
Summary: Nuxeo REST API Python client
Home-page: https://github.com/nuxeo/nuxeo-python-client
Author: Nuxeo
Author-email: maintainers-python@nuxeo.com
License: Apache Software
Keywords: api,rest,automation,client,nuxeo,ecm
Classifier: Development Status :: 5 - Production/Stable
Classifier: Intended Audience :: Developers
Classifier: License :: OSI Approved :: Apache Software License
Classifier: Natural Language :: English
Classifier: Operating System :: OS Independent
Classifier: Programming Language :: Python :: 3
Classifier: Programming Language :: Python :: 3.7
Classifier: Programming Language :: Python :: 3.8
Classifier: Programming Language :: Python :: 3.9
Classifier: Programming Language :: Python :: 3.10
Classifier: Topic :: Software Development :: Libraries
License-File: LICENSE.txt
Requires-Dist: requests>=2.12.2
Provides-Extra: oauth2
Requires-Dist: authlib>=0.15.3; extra == "oauth2"
Requires-Dist: jwt>=1.2.0; extra == "oauth2"
Provides-Extra: s3
Requires-Dist: boto3>=1.10.48; extra == "s3"
